dnslist
