Metadata-Version: 1.2
Name: dnslist
Version: 0.2
Summary: Domain list generator
Home-page: https://github.com/marmeladema/dnslist/
Author: Elie ROUDNINSKI
Author-email: xademax@gmail.com
License: UNKNOWN
Download-URL: https://github.com/marmeladema/dnslist/archive/0.2.tar.gz
Platform: UNKNOWN
Requires-Python: >=3
